wrfy/__init__.py
wrfy/check.py
wrfy/cli.py
wrfy/container.py
wrfy/image.py
wrfy/util.py
wrfy/volume.py
wrfy-0.9.2.dist-info/LICENSE
wrfy-0.9.2.dist-info/WHEEL
wrfy-0.9.2.dist-info/entry_points.txt
wrfy-0.9.2.dist-info/METADATA
wrfy-0.9.2.dist-info/RECORD
