Metadata-Version: 2.1
Name: wrfy
Version: 0.9.2
Summary: Simple bulk operations for Docker
Author: Grahame Bowland
Author-email: grahame@oreamnos.com.au
Requires-Python: >=3.7,<4
Classifier: Programming Language :: Python :: 3
Classifier: Programming Language :: Python :: 3.7
Classifier: Programming Language :: Python :: 3.8
Classifier: Programming Language :: Python :: 3.9
Classifier: Programming Language :: Python :: 3.10
Classifier: Programming Language :: Python :: 3.11
Requires-Dist: docker (>=2.7.0,<3.0.0)
Requires-Dist: progressbar2 (>=3.55.0,<4.0.0)
